cavitometer_deconvolve/__init__.py
cavitometer_deconvolve/GUI/__init__.py
cavitometer_deconvolve/GUI/main.py
cavitometer_deconvolve/hardware/__init__.py
cavitometer_deconvolve/hardware/sensitivities.py
cavitometer_deconvolve/math/FFT.py
cavitometer_deconvolve/math/__init__.py
cavitometer_deconvolve/math/convert.py
cavitometer_deconvolve/math/deconvolve.py
cavitometer_deconvolve/utils/__init__.py
cavitometer_deconvolve/utils/read.py
cavitometer_deconvolve/utils/walker.py
cavitometer_deconvolve-0.4.1.dist-info/METADATA
cavitometer_deconvolve-0.4.1.dist-info/WHEEL
cavitometer_deconvolve-0.4.1.dist-info/licenses/LICENSE
cavitometer_deconvolve-0.4.1.dist-info/RECORD
