Metadata-Version: 2.1
Name: cavitometer-deconvolve
Version: 0.4.1
Summary: Hydrophone voltage to pressure conversion
Project-URL: Homepage, https://github.com/blebon/cavitometer-deconvolve
Project-URL: Documentation, https://blebon.com/cavitometer-deconvolve
Project-URL: Repository, https://github.com/blebon/cavitometer-deconvolve.git
Project-URL: Issue Tracker, https://github.com/blebon/cavitometer-deconvolve/issues
Author-email: Bruno Lebon <Bruno.Lebon@brunel.ac.uk>
License:                     GNU GENERAL PUBLIC LICENSE
License-File: LICENSE
Keywords: cavitometer,deconvolution,hydrophone
Classifier: License :: OSI Approved :: GNU General Public License v3 (GPLv3)
Classifier: Operating System :: OS Independent
Classifier: Programming Language :: Python :: 3
Requires-Python: >=3.10
Provides-Extra: doc
Requires-Dist: sphinx; extra == 'doc'
Provides-Extra: test
Requires-Dist: pytest; extra == 'test'
Requires-Dist: pytest-env; extra == 'test'
Requires-Dist: pytest-qt; extra == 'test'
